first_llms/data_process.cpython-310-x86_64-linux-gnu.so
first_llms/llm_chat.cpython-310-x86_64-linux-gnu.so
first_llms/llm_rag.cpython-310-x86_64-linux-gnu.so
first_llms/prompts.cpython-310-x86_64-linux-gnu.so
first_llms/vec_store.cpython-310-x86_64-linux-gnu.so
first_llms-0.1.21.dist-info/METADATA
first_llms-0.1.21.dist-info/WHEEL
first_llms-0.1.21.dist-info/top_level.txt
first_llms-0.1.21.dist-info/RECORD
